[
    {
        "event": {
            "reo": "reo::Intrinsic_reach",
            "ere": "transportperson",
            "lemma": "came",
            "propbank": "come.01",
            "mentionid": "em-1214",
            "modality": "actual",
            "framenet": "fn::Arriving"
        },
        "arguments": [
            {
                "reo": "reo::Theme",
                "ere": "agent",
                "entity": "ent-21",
                "entity-ner": "PER",
                "entity-specificity": "specific",
                "entity-text": "she"
            },
            {
                "reo": "reo::Destination",
                "ere": "destination",
                "entity": "ent-81",
                "entity-ner": "GPE",
                "entity-specificity": "specific",
                "entity-text": "Italy"
            }
        ]
    },
    {
        "event": {
            "reo": "reo::Birth",
            "ere": "beborn",
            "lemma": "born",
            "propbank": "born.XX",
            "mentionid": "em-1235",
            "modality": "actual",
            "framenet": "fn::Being_born"
        },
        "arguments": [
            {
                "reo": "reo::Child",
                "ere": "person",
                "entity": "ent-24",
                "entity-ner": "PER",
                "entity-specificity": "specific",
                "entity-text": "BabyD"
            },
            {
                "reo": "reo::place",
                "ere": "place",
                "entity": "ent-81",
                "entity-ner": "GPE",
                "entity-specificity": "specific",
                "entity-text": "Italy"
            }
        ]
    },
    {
        "event": {
            "reo": "reo::Instrument_Communication",
            "ere": "correspondence",
            "lemma": "called",
            "propbank": "call.07",
            "mentionid": "em-1256",
            "modality": "actual",
            "framenet": "fn::Contacting"
        },
        "arguments": [
            {
                "reo": "reo::Recipient",
                "ere": "entity",
                "entity": "ent-27",
                "entity-ner": "PER",
                "entity-specificity": "specific",
                "entity-text": "my dad"
            }
        ]
    },
    {
        "event": {
            "reo": "reo::Instrument_Communication",
            "ere": "correspondence",
            "lemma": "call",
            "propbank": "call.07",
            "mentionid": "em-1893",
            "modality": "other",
            "framenet": "fn::Communication_means"
        },
        "arguments": [
            {
                "reo": "reo::Recipient",
                "ere": "entity",
                "entity": "ent-8",
                "entity-ner": "PER",
                "entity-specificity": "specific",
                "entity-text": "I"
            }
        ]
    },
    {
        "event": {
            "reo": "reo::Intrinsic_reach",
            "ere": "transportperson",
            "lemma": "came",
            "propbank": "come.01",
            "mentionid": "em-1277",
            "modality": "actual",
            "framenet": "fn::Arriving"
        },
        "arguments": [
            {
                "reo": "reo::Theme",
                "ere": "agent",
                "entity": "ent-21",
                "entity-ner": "PER",
                "entity-specificity": "specific",
                "entity-text": "she"
            },
            {
                "reo": "reo::Destination",
                "ere": "destination",
                "entity": "ent-84",
                "entity-ner": "GPE",
                "entity-specificity": "specific",
                "entity-text": "Bahrain"
            },
            {
                "reo": "reo::time",
                "ere": "time",
                "entity": "f-1498",
                "entity-ner": "time",
                "entity-specificity": "UNK",
                "entity-text": "a year ago"
            }
        ]
    },
    {
        "event": {
            "reo": "reo::Protest_conflict",
            "ere": "demonstrate",
            "lemma": "demonstrations",
            "propbank": "demonstrations.XX",
            "mentionid": "em-1298",
            "modality": "actual",
            "framenet": "fn::Protest"
        },
        "arguments": [
            {
                "reo": "reo::Place",
                "ere": "place",
                "entity": "ent-84",
                "entity-ner": "GPE",
                "entity-specificity": "specific",
                "entity-text": "Bahrain"
            },
            {
                "reo": "reo::Time",
                "ere": "time",
                "entity": "f-1512",
                "entity-ner": "time",
                "entity-specificity": "UNK",
                "entity-text": "a year ago"
            }
        ]
    },
    {
        "event": {
            "reo": "reo::Intrinsic_leave",
            "ere": "transportperson",
            "lemma": "flew",
            "propbank": "fly.06",
            "mentionid": "em-1319",
            "modality": "actual",
            "framenet": "fn::Self_motion"
        },
        "arguments": [
            {
                "reo": "reo::Theme",
                "ere": "person",
                "entity": "ent-8",
                "entity-ner": "PER",
                "entity-specificity": "specific",
                "entity-text": "I"
            },
            {
                "reo": "reo::Destination",
                "ere": "destination",
                "entity": "ent-90",
                "entity-ner": "FAC",
                "entity-specificity": "specific",
                "entity-text": "home"
            }
        ]
    },
    {
        "event": {
            "reo": "reo::Intrinsic_reach",
            "ere": "transportperson",
            "lemma": "comes",
            "propbank": "come.01",
            "mentionid": "em-1340",
            "modality": "actual",
            "framenet": "fn::Arriving"
        },
        "arguments": [
            {
                "reo": "reo::Theme",
                "ere": "agent",
                "entity": "ent-18",
                "entity-ner": "PER",
                "entity-specificity": "specific",
                "entity-text": "He"
            },
            {
                "reo": "reo::Destination",
                "ere": "destination",
                "entity": "ent-96",
                "entity-ner": "FAC",
                "entity-specificity": "specific",
                "entity-text": "home"
            }
        ]
    },
    {
        "event": {
            "reo": "reo::Meet",
            "ere": "meet",
            "lemma": "tells",
            "propbank": "tells.XX",
            "mentionid": "em-1361",
            "modality": "actual",
            "framenet": "fn::Social_event"
        },
        "arguments": [
            {
                "reo": "reo::Meeting_Parties",
                "ere": "entity",
                "entity": "ent-18",
                "entity-ner": "PER",
                "entity-specificity": "specific",
                "entity-text": "he"
            }
        ]
    },
    {
        "event": {
            "reo": "reo::UNK",
            "ere": "meet",
            "lemma": "announce",
            "propbank": "UNK",
            "mentionid": "em-1382",
            "modality": "actual",
            "framenet": "UNK"
        },
        "arguments": [
            {
                "reo": "UNK",
                "ere": "ere::Entity",
                "entity": "ent-8",
                "entity-ner": "PER",
                "entity-specificity": "specific",
                "entity-text": "me"
            },
            {
                "reo": "UNK",
                "ere": "ere::Place",
                "entity": "ent-90",
                "entity-ner": "FAC",
                "entity-specificity": "specific",
                "entity-text": "home"
            }
        ]
    },
    {
        "event": {
            "reo": "reo::UNK",
            "ere": "beborn",
            "lemma": "birth",
            "propbank": "UNK",
            "mentionid": "em-1403",
            "modality": "actual",
            "framenet": "UNK"
        },
        "arguments": [
            {
                "reo": "UNK",
                "ere": "ere::Person",
                "entity": "ent-60",
                "entity-ner": "PER",
                "entity-specificity": "specific",
                "entity-text": "the twins"
            },
            {
                "reo": "UNK",
                "ere": "ere::Place",
                "entity": "ent-1603",
                "entity-ner": "FAC",
                "entity-specificity": "specific",
                "entity-text": "here"
            }
        ]
    },
    {
        "event": {
            "reo": "reo::Statement",
            "ere": "contact",
            "lemma": "told",
            "propbank": "tell.01",
            "mentionid": "em-1424",
            "modality": "actual",
            "framenet": "fn::Statement"
        },
        "arguments": [
            {
                "reo": "reo::Agent",
                "ere": "entity",
                "entity": "ent-54",
                "entity-ner": "PER",
                "entity-specificity": "specific",
                "entity-text": "me"
            },
            {
                "reo": "reo::time",
                "ere": "time",
                "entity": "f-1561",
                "entity-ner": "time",
                "entity-specificity": "UNK",
                "entity-text": "last night"
            }
        ]
    },
    {
        "event": {
            "reo": "reo::Marry",
            "ere": "marry",
            "lemma": "wedding",
            "propbank": "wed.01",
            "mentionid": "em-1445",
            "modality": "actual",
            "framenet": "fn::Forming_relationships"
        },
        "arguments": [
            {
                "reo": "reo::Couple",
                "ere": "person",
                "entity": "ent-30",
                "entity-ner": "PER",
                "entity-specificity": "specific",
                "entity-text": "my brother"
            }
        ]
    },
    {
        "event": {
            "reo": "reo::Intrinsic_leave",
            "ere": "transportperson",
            "lemma": "leaves",
            "propbank": "leave.11",
            "mentionid": "em-1775",
            "modality": "other",
            "framenet": "fn::Departing"
        },
        "arguments": [
            {
                "reo": "reo::Theme",
                "ere": "agent",
                "entity": "ent-18",
                "entity-ner": "PER",
                "entity-specificity": "specific",
                "entity-text": "DH"
            },
            {
                "reo": "reo::time",
                "ere": "time",
                "entity": "f-1800",
                "entity-ner": "time",
                "entity-specificity": "UNK",
                "entity-text": "tonight"
            }
        ]
    },
    {
        "event": {
            "reo": "reo::Intrinsic_leave",
            "ere": "transportperson",
            "lemma": "flight",
            "propbank": "fly.01",
            "mentionid": "em-1805",
            "modality": "other",
            "framenet": "fn::Escaping"
        },
        "arguments": [
            {
                "reo": "reo::Theme",
                "ere": "person",
                "entity": "ent-21",
                "entity-ner": "PER",
                "entity-specificity": "specific",
                "entity-text": "my mother"
            },
            {
                "reo": "reo::Destination",
                "ere": "destination",
                "entity": "ent-1676",
                "entity-ner": "FAC",
                "entity-specificity": "specific",
                "entity-text": "here"
            }
        ]
    },
    {
        "event": {
            "reo": "reo::UNK",
            "ere": "meet",
            "lemma": "visit",
            "propbank": "UNK",
            "mentionid": "em-1835",
            "modality": "actual",
            "framenet": "UNK"
        },
        "arguments": [
            {
                "reo": "UNK",
                "ere": "ere::Entity",
                "entity": "ent-21",
                "entity-ner": "PER",
                "entity-specificity": "specific",
                "entity-text": "she"
            },
            {
                "reo": "UNK",
                "ere": "ere::Place",
                "entity": "ent-81",
                "entity-ner": "GPE",
                "entity-specificity": "specific",
                "entity-text": "Italy"
            }
        ]
    },
    {
        "event": {
            "reo": "reo::UNK",
            "ere": "meet",
            "lemma": "visit",
            "propbank": "UNK",
            "mentionid": "em-1865",
            "modality": "actual",
            "framenet": "UNK"
        },
        "arguments": [
            {
                "reo": "UNK",
                "ere": "ere::Entity",
                "entity": "ent-8",
                "entity-ner": "PER",
                "entity-specificity": "specific",
                "entity-text": "I"
            }
        ]
    },
    {
        "event": {
            "reo": "reo::Experience_Injury",
            "ere": "injure",
            "lemma": "broken",
            "propbank": "break.01",
            "mentionid": "em-1914",
            "modality": "actual",
            "framenet": "fn::Experience_bodily_harm"
        },
        "arguments": [
            {
                "reo": "reo::Victim",
                "ere": "victim",
                "entity": "ent-21",
                "entity-ner": "PER",
                "entity-specificity": "specific",
                "entity-text": "She"
            }
        ]
    },
    {
        "event": {
            "reo": "reo::Intrinsic_change_location",
            "ere": "transportperson",
            "lemma": "cruise",
            "propbank": "cruise.01",
            "mentionid": "em-1937",
            "modality": "actual",
            "framenet": "fn::Self_motion"
        },
        "arguments": [
            {
                "reo": "reo::Mover",
                "ere": "person",
                "entity": "ent-57",
                "entity-ner": "PER",
                "entity-specificity": "specific",
                "entity-text": "she"
            },
            {
                "reo": "reo::Initial_Location",
                "ere": "origin",
                "entity": "ent-99",
                "entity-ner": "LOC",
                "entity-specificity": "specific",
                "entity-text": "Thames river"
            },
            {
                "reo": "reo::Destination",
                "ere": "destination",
                "entity": "ent-99",
                "entity-ner": "LOC",
                "entity-specificity": "specific",
                "entity-text": "Thames river"
            }
        ]
    },
    {
        "event": {
            "reo": "reo::Intrinsic_change_location",
            "ere": "transportperson",
            "lemma": "touring",
            "propbank": "tour.01",
            "mentionid": "em-1974",
            "modality": "actual",
            "framenet": "UNK"
        },
        "arguments": [
            {
                "reo": "reo::Mover",
                "ere": "agent",
                "entity": "ent-63",
                "entity-ner": "PER",
                "entity-specificity": "specific",
                "entity-text": "They"
            },
            {
                "reo": "reo::Initial_Location",
                "ere": "origin",
                "entity": "ent-87",
                "entity-ner": "GPE",
                "entity-specificity": "specific",
                "entity-text": "London"
            },
            {
                "reo": "reo::Destination",
                "ere": "destination",
                "entity": "ent-87",
                "entity-ner": "GPE",
                "entity-specificity": "specific",
                "entity-text": "London"
            }
        ]
    },
    {
        "event": {
            "reo": "reo::Intrinsic_reach",
            "ere": "transportperson",
            "lemma": "come",
            "propbank": "come.01",
            "mentionid": "em-2011",
            "modality": "other",
            "framenet": "fn::Arriving"
        },
        "arguments": [
            {
                "reo": "reo::Theme",
                "ere": "agent",
                "entity": "ent-18",
                "entity-ner": "PER",
                "entity-specificity": "specific",
                "entity-text": "he"
            },
            {
                "reo": "reo::Destination",
                "ere": "destination",
                "entity": "ent-96",
                "entity-ner": "FAC",
                "entity-specificity": "specific",
                "entity-text": "home"
            },
            {
                "reo": "reo::time",
                "ere": "time",
                "entity": "f-2043",
                "entity-ner": "time",
                "entity-specificity": "UNK",
                "entity-text": "Sunday"
            }
        ]
    },
    {
        "event": {
            "reo": "reo::Intrinsic_reach",
            "ere": "transportperson",
            "lemma": "come",
            "propbank": "come.01",
            "mentionid": "em-2048",
            "modality": "actual",
            "framenet": "fn::Arriving"
        },
        "arguments": [
            {
                "reo": "reo::Theme",
                "ere": "agent",
                "entity": "ent-72",
                "entity-ner": "PER",
                "entity-specificity": "specific",
                "entity-text": "MIL"
            },
            {
                "reo": "reo::Destination",
                "ere": "destination",
                "entity": "ent-1603",
                "entity-ner": "FAC",
                "entity-specificity": "specific",
                "entity-text": "here"
            }
        ]
    },
    {
        "event": {
            "reo": "reo::UNK",
            "ere": "transportperson",
            "lemma": "sent",
            "propbank": "UNK",
            "mentionid": "em-2078",
            "modality": "other",
            "framenet": "UNK"
        },
        "arguments": [
            {
                "reo": "UNK",
                "ere": "ere::Agent",
                "entity": "ent-69",
                "entity-ner": "PER",
                "entity-specificity": "specific",
                "entity-text": "DH"
            },
            {
                "reo": "UNK",
                "ere": "ere::Person",
                "entity": "ent-72",
                "entity-ner": "PER",
                "entity-specificity": "specific",
                "entity-text": "her"
            },
            {
                "reo": "UNK",
                "ere": "ere::Instrument",
                "entity": "f-2110",
                "entity-ner": "vehicle",
                "entity-specificity": "UNK",
                "entity-text": "plane"
            },
            {
                "reo": "UNK",
                "ere": "ere::Origin",
                "entity": "ent-1603",
                "entity-ner": "FAC",
                "entity-specificity": "specific",
                "entity-text": "here"
            }
        ]
    },
    {
        "event": {
            "reo": "reo::UNK",
            "ere": "meet",
            "lemma": "visit",
            "propbank": "UNK",
            "mentionid": "em-2122",
            "modality": "other",
            "framenet": "UNK"
        },
        "arguments": [
            {
                "reo": "UNK",
                "ere": "ere::Entity",
                "entity": "ent-8",
                "entity-ner": "PER",
                "entity-specificity": "specific",
                "entity-text": "your"
            }
        ]
    },
    {
        "event": {
            "reo": "reo::UNK",
            "ere": "meet",
            "lemma": "visit",
            "propbank": "UNK",
            "mentionid": "em-2152",
            "modality": "other",
            "framenet": "UNK"
        },
        "arguments": [
            {
                "reo": "UNK",
                "ere": "ere::Entity",
                "entity": "ent-8",
                "entity-ner": "PER",
                "entity-specificity": "specific",
                "entity-text": "my"
            },
            {
                "reo": "UNK",
                "ere": "ere::Place",
                "entity": "ent-1676",
                "entity-ner": "FAC",
                "entity-specificity": "specific",
                "entity-text": "here"
            }
        ]
    },
    {
        "event": {
            "reo": "reo::Send",
            "ere": "transportperson",
            "lemma": "send",
            "propbank": "send.01",
            "mentionid": "em-2275",
            "modality": "generic",
            "framenet": "fn::Sending"
        },
        "arguments": [
            {
                "reo": "reo::Agent",
                "ere": "agent",
                "entity": "ent-27",
                "entity-ner": "PER",
                "entity-specificity": "specific",
                "entity-text": "my dad"
            },
            {
                "reo": "reo::Theme",
                "ere": "person",
                "entity": "ent-21",
                "entity-ner": "PER",
                "entity-specificity": "specific",
                "entity-text": "her"
            },
            {
                "reo": "reo::Initial_Location",
                "ere": "origin",
                "entity": "ent-90",
                "entity-ner": "FAC",
                "entity-specificity": "specific",
                "entity-text": "home"
            }
        ]
    }
]