[
    {
        "event": {
            "reo": "reo::Give",
            "ere": "transfermoney",
            "lemma": "gave",
            "propbank": "give.01",
            "mentionid": "em-592",
            "modality": "actual",
            "framenet": "fn::Giving"
        },
        "arguments": [
            {
                "reo": "reo::Donor",
                "ere": "giver",
                "entity": "ent-63",
                "entity-ner": "ORG",
                "entity-specificity": "specificIndividual",
                "entity-text": "Microsoft"
            },
            {
                "reo": "reo::Recipient",
                "ere": "recipient",
                "entity": "ent-8",
                "entity-ner": "ORG",
                "entity-specificity": "specificIndividual",
                "entity-text": "them"
            }
        ]
    },
    {
        "event": {
            "reo": "reo::Give",
            "ere": "transfermoney",
            "lemma": "paid",
            "propbank": "pay.01",
            "mentionid": "em-766",
            "modality": "actual",
            "framenet": "UNK"
        },
        "arguments": [
            {
                "reo": "reo::Donor",
                "ere": "giver",
                "entity": "ent-63",
                "entity-ner": "ORG",
                "entity-specificity": "specificIndividual",
                "entity-text": "MS"
            },
            {
                "reo": "reo::Recipient",
                "ere": "recipient",
                "entity": "ent-8",
                "entity-ner": "ORG",
                "entity-specificity": "specificIndividual",
                "entity-text": "them"
            }
        ]
    },
    {
        "event": {
            "reo": "reo::Give",
            "ere": "transfermoney",
            "lemma": "pay",
            "propbank": "pay.01",
            "mentionid": "em-1018",
            "modality": "other",
            "framenet": "UNK"
        },
        "arguments": [
            {
                "reo": "reo::Donor",
                "ere": "giver",
                "entity": "ent-63",
                "entity-ner": "ORG",
                "entity-specificity": "specificIndividual",
                "entity-text": "Microsoft"
            },
            {
                "reo": "reo::Recipient",
                "ere": "recipient",
                "entity": "ent-402",
                "entity-ner": "ORG",
                "entity-specificity": "nonspecific",
                "entity-text": "a partner"
            }
        ]
    },
    {
        "event": {
            "reo": "reo::Give",
            "ere": "transfermoney",
            "lemma": "given",
            "propbank": "give.01",
            "mentionid": "em-1261",
            "modality": "actual",
            "framenet": "fn::Giving"
        },
        "arguments": [
            {
                "reo": "reo::Donor",
                "ere": "giver",
                "entity": "ent-63",
                "entity-ner": "ORG",
                "entity-specificity": "specificIndividual",
                "entity-text": "MS"
            }
        ]
    },
    {
        "event": {
            "reo": "reo::Buy_sell",
            "ere": "transferownership",
            "lemma": "buy",
            "propbank": "buy.01",
            "mentionid": "em-620",
            "modality": "other",
            "framenet": "fn::Commerce_buy"
        },
        "arguments": [
            {
                "reo": "reo::Recipient",
                "ere": "recipient",
                "entity": "ent-117",
                "entity-ner": "PER",
                "entity-specificity": "specificIndividual",
                "entity-text": "I"
            },
            {
                "reo": "reo::Donor",
                "ere": "giver",
                "entity": "ent-8",
                "entity-ner": "ORG",
                "entity-specificity": "specificIndividual",
                "entity-text": "Nokia"
            },
            {
                "reo": "reo::Theme",
                "ere": "thing",
                "entity": "f-652",
                "entity-ner": "commodity",
                "entity-specificity": "UNK",
                "entity-text": "Nokia Android hardware"
            }
        ]
    },
    {
        "event": {
            "reo": "reo::Buy_sell",
            "ere": "transfermoney",
            "lemma": "buy",
            "propbank": "buy.01",
            "mentionid": "em-657",
            "modality": "other",
            "framenet": "fn::Commerce_buy"
        },
        "arguments": [
            {
                "reo": "reo::Donor",
                "ere": "giver",
                "entity": "ent-117",
                "entity-ner": "PER",
                "entity-specificity": "specificIndividual",
                "entity-text": "I"
            },
            {
                "reo": "reo::Recipient",
                "ere": "recipient",
                "entity": "ent-8",
                "entity-ner": "ORG",
                "entity-specificity": "specificIndividual",
                "entity-text": "Nokia"
            }
        ]
    },
    {
        "event": {
            "reo": "reo::UNK",
            "ere": "artifact",
            "lemma": "manufacturer",
            "propbank": "UNK",
            "mentionid": "em-1046",
            "modality": "generic",
            "framenet": "UNK"
        },
        "arguments": [
            {
                "reo": "UNK",
                "ere": "ere::Agent",
                "entity": "ent-8",
                "entity-ner": "ORG",
                "entity-specificity": "specificIndividual",
                "entity-text": "the number 1 Windows Phone manufacturer"
            },
            {
                "reo": "UNK",
                "ere": "ere::Artifact",
                "entity": "f-1071",
                "entity-ner": "commodity",
                "entity-specificity": "UNK",
                "entity-text": "Windows Phone"
            }
        ]
    },
    {
        "event": {
            "reo": "reo::UNK",
            "ere": "artifact",
            "lemma": "OEM",
            "propbank": "UNK",
            "mentionid": "em-687",
            "modality": "other",
            "framenet": "UNK"
        },
        "arguments": [
            {
                "reo": "UNK",
                "ere": "ere::Agent",
                "entity": "ent-708",
                "entity-ner": "ORG",
                "entity-specificity": "nonspecific",
                "entity-text": "the premier Windows Phone OEM"
            },
            {
                "reo": "UNK",
                "ere": "ere::Artifact",
                "entity": "f-715",
                "entity-ner": "commodity",
                "entity-specificity": "UNK",
                "entity-text": "Windows Phone"
            }
        ]
    },
    {
        "event": {
            "reo": "reo::UNK",
            "ere": "correspondence",
            "lemma": "poster",
            "propbank": "UNK",
            "mentionid": "em-743",
            "modality": "actual",
            "framenet": "UNK"
        },
        "arguments": [
            {
                "reo": "UNK",
                "ere": "ere::Entity",
                "entity": "ent-78",
                "entity-ner": "PER",
                "entity-specificity": "specificIndividual",
                "entity-text": "the second poster"
            }
        ]
    },
    {
        "event": {
            "reo": "reo::Give",
            "ere": "transfermoney",
            "lemma": "pays",
            "propbank": "pay.01",
            "mentionid": "em-815",
            "modality": "generic",
            "framenet": "UNK"
        },
        "arguments": [
            {
                "reo": "reo::Donor",
                "ere": "giver",
                "entity": "ent-8",
                "entity-ner": "ORG",
                "entity-specificity": "specificIndividual",
                "entity-text": "Nokia"
            }
        ]
    },
    {
        "event": {
            "reo": "reo::Give",
            "ere": "transferownership",
            "lemma": "pays",
            "propbank": "pay.01",
            "mentionid": "em-838",
            "modality": "generic",
            "framenet": "UNK"
        },
        "arguments": [
            {
                "reo": "reo::Recipient",
                "ere": "recipient",
                "entity": "ent-8",
                "entity-ner": "ORG",
                "entity-specificity": "specificIndividual",
                "entity-text": "Nokia"
            },
            {
                "reo": "reo::Theme",
                "ere": "thing",
                "entity": "f-863",
                "entity-ner": "commodity",
                "entity-specificity": "UNK",
                "entity-text": "licenses"
            }
        ]
    },
    {
        "event": {
            "reo": "reo::Give",
            "ere": "transferownership",
            "lemma": "gifts",
            "propbank": "gift.01",
            "mentionid": "em-868",
            "modality": "actual",
            "framenet": "fn::Giving"
        },
        "arguments": [
            {
                "reo": "reo::Donor",
                "ere": "giver",
                "entity": "ent-8",
                "entity-ner": "ORG",
                "entity-specificity": "specificIndividual",
                "entity-text": "they"
            },
            {
                "reo": "reo::Theme",
                "ere": "thing",
                "entity": "f-893",
                "entity-ner": "commodity",
                "entity-specificity": "UNK",
                "entity-text": "patent"
            }
        ]
    },
    {
        "event": {
            "reo": "reo::UNK",
            "ere": "artifact",
            "lemma": "manufacturer",
            "propbank": "UNK",
            "mentionid": "em-988",
            "modality": "other",
            "framenet": "UNK"
        },
        "arguments": [
            {
                "reo": "UNK",
                "ere": "ere::Agent",
                "entity": "ent-369",
                "entity-ner": "ORG",
                "entity-specificity": "nonspecific",
                "entity-text": "just another android manufacturer"
            },
            {
                "reo": "UNK",
                "ere": "ere::Artifact",
                "entity": "f-1013",
                "entity-ner": "commodity",
                "entity-specificity": "UNK",
                "entity-text": "android"
            }
        ]
    },
    {
        "event": {
            "reo": "reo::UNK",
            "ere": "artifact",
            "lemma": "manufacturer",
            "propbank": "UNK",
            "mentionid": "em-1074",
            "modality": "generic",
            "framenet": "UNK"
        },
        "arguments": [
            {
                "reo": "UNK",
                "ere": "ere::Agent",
                "entity": "ent-189",
                "entity-ner": "ORG",
                "entity-specificity": "specificIndividual",
                "entity-text": "the only other notable WP manufacturer"
            },
            {
                "reo": "UNK",
                "ere": "ere::Artifact",
                "entity": "f-1099",
                "entity-ner": "commodity",
                "entity-specificity": "UNK",
                "entity-text": "WP"
            }
        ]
    },
    {
        "event": {
            "reo": "reo::Buy_sell",
            "ere": "transferownership",
            "lemma": "sold",
            "propbank": "sell.01",
            "mentionid": "em-1104",
            "modality": "other",
            "framenet": "fn::Commerce_sell"
        },
        "arguments": [
            {
                "reo": "reo::Theme",
                "ere": "thing",
                "entity": "f-1121",
                "entity-ner": "commodity",
                "entity-specificity": "UNK",
                "entity-text": "the single device that was allowed to be sold IN MINOR MARKETS"
            }
        ]
    },
    {
        "event": {
            "reo": "reo::Buy_sell",
            "ere": "transferownership",
            "lemma": "selling",
            "propbank": "sell.01",
            "mentionid": "em-1173",
            "modality": "actual",
            "framenet": "fn::Commerce_sell"
        },
        "arguments": [
            {
                "reo": "reo::Theme",
                "ere": "thing",
                "entity": "f-1485",
                "entity-ner": "commodity",
                "entity-specificity": "UNK",
                "entity-text": "the single device that was allowed to be sold IN MINOR MARKETS"
            }
        ]
    },
    {
        "event": {
            "reo": "reo::Buy_sell",
            "ere": "transferownership",
            "lemma": "selling",
            "propbank": "sell.01",
            "mentionid": "em-1215",
            "modality": "actual",
            "framenet": "fn::Commerce_sell"
        },
        "arguments": [
            {
                "reo": "reo::Theme",
                "ere": "thing",
                "entity": "f-1232",
                "entity-ner": "commodity",
                "entity-specificity": "UNK",
                "entity-text": "WP"
            }
        ]
    },
    {
        "event": {
            "reo": "reo::Give",
            "ere": "transfermoney",
            "lemma": "give",
            "propbank": "give.01",
            "mentionid": "em-1282",
            "modality": "other",
            "framenet": "fn::Giving"
        },
        "arguments": [
            {
                "reo": "reo::Donor",
                "ere": "giver",
                "entity": "ent-63",
                "entity-ner": "ORG",
                "entity-specificity": "specificIndividual",
                "entity-text": "MS"
            },
            {
                "reo": "reo::Recipient",
                "ere": "recipient",
                "entity": "ent-8",
                "entity-ner": "ORG",
                "entity-specificity": "specificIndividual",
                "entity-text": "Nokia"
            }
        ]
    },
    {
        "event": {
            "reo": "reo::UNK",
            "ere": "transfermoney",
            "lemma": "way",
            "propbank": "UNK",
            "mentionid": "em-1312",
            "modality": "generic",
            "framenet": "UNK"
        },
        "arguments": [
            {
                "reo": "UNK",
                "ere": "ere::Giver",
                "entity": "ent-8",
                "entity-ner": "ORG",
                "entity-specificity": "specificIndividual",
                "entity-text": "Nokia"
            },
            {
                "reo": "UNK",
                "ere": "ere::Recipient",
                "entity": "ent-63",
                "entity-ner": "ORG",
                "entity-specificity": "specificIndividual",
                "entity-text": "MS"
            }
        ]
    },
    {
        "event": {
            "reo": "reo::UNK",
            "ere": "artifact",
            "lemma": "manufacturer",
            "propbank": "UNK",
            "mentionid": "em-1342",
            "modality": "generic",
            "framenet": "UNK"
        },
        "arguments": [
            {
                "reo": "UNK",
                "ere": "ere::Agent",
                "entity": "ent-8",
                "entity-ner": "ORG",
                "entity-specificity": "specificIndividual",
                "entity-text": "just another Windows Phone manufacturer"
            },
            {
                "reo": "UNK",
                "ere": "ere::Artifact",
                "entity": "f-1388",
                "entity-ner": "commodity",
                "entity-specificity": "UNK",
                "entity-text": "Windows Phone"
            }
        ]
    },
    {
        "event": {
            "reo": "reo::UNK",
            "ere": "artifact",
            "lemma": "lines",
            "propbank": "UNK",
            "mentionid": "em-1488",
            "modality": "generic",
            "framenet": "UNK"
        },
        "arguments": [
            {
                "reo": "UNK",
                "ere": "ere::Agent",
                "entity": "ent-189",
                "entity-ner": "ORG",
                "entity-specificity": "specificIndividual",
                "entity-text": "HTC"
            },
            {
                "reo": "UNK",
                "ere": "ere::Artifact",
                "entity": "f-1513",
                "entity-ner": "commodity",
                "entity-specificity": "UNK",
                "entity-text": "android"
            }
        ]
    },
    {
        "event": {
            "reo": "reo::Give",
            "ere": "transferownership",
            "lemma": "giving",
            "propbank": "give.01",
            "mentionid": "em-1421",
            "modality": "actual",
            "framenet": "fn::Giving"
        },
        "arguments": [
            {
                "reo": "reo::Donor",
                "ere": "giver",
                "entity": "ent-63",
                "entity-ner": "ORG",
                "entity-specificity": "specificIndividual",
                "entity-text": "MS"
            },
            {
                "reo": "reo::Recipient",
                "ere": "recipient",
                "entity": "ent-558",
                "entity-ner": "ORG",
                "entity-specificity": "specificGroup",
                "entity-text": "every other manufacturer"
            },
            {
                "reo": "reo::Theme",
                "ere": "thing",
                "entity": "f-1453",
                "entity-ner": "commodity",
                "entity-specificity": "UNK",
                "entity-text": "Nokia's maps and other software"
            }
        ]
    },
    {
        "event": {
            "reo": "reo::UNK",
            "ere": "artifact",
            "lemma": "manufacturer",
            "propbank": "UNK",
            "mentionid": "em-1458",
            "modality": "generic",
            "framenet": "UNK"
        },
        "arguments": [
            {
                "reo": "UNK",
                "ere": "ere::Agent",
                "entity": "ent-558",
                "entity-ner": "ORG",
                "entity-specificity": "specificGroup",
                "entity-text": "every other manufacturer"
            }
        ]
    }
]