[
    {
        "event": {
            "reo": "reo::Kill",
            "ere": "die",
            "lemma": "claimed",
            "propbank": "claimed.XX",
            "mentionid": "em-1610",
            "modality": "actual",
            "framenet": "fn::Killing"
        },
        "arguments": [
            {
                "reo": "reo::Victim",
                "ere": "victim",
                "entity": "ent-618",
                "entity-ner": "PER",
                "entity-specificity": "specificGroup",
                "entity-text": "5,670 lives"
            }
        ]
    },
    {
        "event": {
            "reo": "reo::UNK",
            "ere": "artifact",
            "lemma": "reconstruction",
            "propbank": "UNK",
            "mentionid": "em-1044",
            "modality": "other",
            "framenet": "UNK"
        },
        "arguments": [
            {
                "reo": "UNK",
                "ere": "ere::Agent",
                "entity": "ent-39",
                "entity-ner": "GPE",
                "entity-specificity": "specificIndividual",
                "entity-text": "the country"
            }
        ]
    },
    {
        "event": {
            "reo": false,
            "ere": "artifact",
            "lemma": "reconstruction",
            "propbank": "reconstruct.01",
            "mentionid": "em-1483",
            "modality": "actual",
            "framenet": "UNK"
        },
        "arguments": [
            {
                "reo": "reo::place",
                "ere": "place",
                "entity": "ent-30",
                "entity-ner": "LOC",
                "entity-specificity": "specificIndeterminate",
                "entity-text": "typhoon-hit areas"
            }
        ]
    },
    {
        "event": {
            "reo": "reo::UNK",
            "ere": "artifact",
            "lemma": "reconstruction",
            "propbank": "UNK",
            "mentionid": "em-1675",
            "modality": "other",
            "framenet": "UNK"
        },
        "arguments": [
            {
                "reo": "UNK",
                "ere": "ere::Agent",
                "entity": "ent-39",
                "entity-ner": "GPE",
                "entity-specificity": "specificIndividual",
                "entity-text": "Philippines"
            }
        ]
    },
    {
        "event": {
            "reo": "reo::Give",
            "ere": "transferownership",
            "lemma": "provided",
            "propbank": "provide.01",
            "mentionid": "em-1009",
            "modality": "actual",
            "framenet": "fn::Supply"
        },
        "arguments": [
            {
                "reo": "reo::Donor",
                "ere": "giver",
                "entity": "ent-8",
                "entity-ner": "GPE",
                "entity-specificity": "specificIndividual",
                "entity-text": "China"
            },
            {
                "reo": "reo::time",
                "ere": "time",
                "entity": "f-1034",
                "entity-ner": "time",
                "entity-specificity": "UNK",
                "entity-text": "Monday"
            },
            {
                "reo": "reo::Theme",
                "ere": "thing",
                "entity": "f-1041",
                "entity-ner": "vehicle",
                "entity-specificity": "UNK",
                "entity-text": "a batch of payloaders which are badly needed in the clean-up of roads in typhoon-devastated areas in central Philippines as the country embarks on the road of reconstruction"
            }
        ]
    },
    {
        "event": {
            "reo": "reo::Give",
            "ere": "transferownership",
            "lemma": "handed over",
            "propbank": "hand.01",
            "mentionid": "em-1067",
            "modality": "actual",
            "framenet": "fn::Giving"
        },
        "arguments": [
            {
                "reo": "reo::Theme",
                "ere": "thing",
                "entity": "f-1084",
                "entity-ner": "vehicle",
                "entity-specificity": "UNK",
                "entity-text": "Three payloader trucks"
            },
            {
                "reo": "reo::Recipient",
                "ere": "recipient",
                "entity": "ent-153",
                "entity-ner": "ORG",
                "entity-specificity": "specificIndividual",
                "entity-text": "Philippine Red Cross Society"
            },
            {
                "reo": "reo::place",
                "ere": "place",
                "entity": "ent-174",
                "entity-ner": "FAC",
                "entity-specificity": "specificIndividual",
                "entity-text": "PRCS headquarters in Manila"
            }
        ]
    },
    {
        "event": {
            "reo": "reo::Give",
            "ere": "transferownership",
            "lemma": "donated",
            "propbank": "donate.01",
            "mentionid": "em-1104",
            "modality": "actual",
            "framenet": "fn::Giving"
        },
        "arguments": [
            {
                "reo": "reo::Theme",
                "ere": "thing",
                "entity": "f-1121",
                "entity-ner": "vehicle",
                "entity-specificity": "UNK",
                "entity-text": "Three payloader trucks"
            },
            {
                "reo": "reo::Donor",
                "ere": "giver",
                "entity": "ent-195",
                "entity-ner": "ORG",
                "entity-specificity": "specificIndividual",
                "entity-text": "Association of Chinese Enterprises"
            }
        ]
    },
    {
        "event": {
            "reo": "reo::Give",
            "ere": "transferownership",
            "lemma": "donated",
            "propbank": "donate.01",
            "mentionid": "em-1582",
            "modality": "actual",
            "framenet": "fn::Giving"
        },
        "arguments": [
            {
                "reo": "reo::Theme",
                "ere": "thing",
                "entity": "f-1599",
                "entity-ner": "vehicle",
                "entity-specificity": "UNK",
                "entity-text": "The payloaders, valued at nearly 8 million pesos"
            },
            {
                "reo": "reo::Donor",
                "ere": "giver",
                "entity": "ent-591",
                "entity-ner": "ORG",
                "entity-specificity": "specificGroup",
                "entity-text": "the 40-plus members of the Chinese enterprises association"
            }
        ]
    },
    {
        "event": {
            "reo": "reo::Statement",
            "ere": "contact",
            "lemma": "said",
            "propbank": "say.01",
            "mentionid": "em-1132",
            "modality": "actual",
            "framenet": "fn::Statement"
        },
        "arguments": [
            {
                "reo": "reo::Agent",
                "ere": "entity",
                "entity": "ent-240",
                "entity-ner": "PER",
                "entity-specificity": "specificIndividual",
                "entity-text": "Ma Keqing"
            }
        ]
    },
    {
        "event": {
            "reo": "reo::Give",
            "ere": "transfermoney",
            "lemma": "donation",
            "propbank": "donate.01",
            "mentionid": "em-1155",
            "modality": "actual",
            "framenet": "fn::Giving"
        },
        "arguments": [
            {
                "reo": "reo::CostOrCotheme",
                "ere": "money",
                "entity": "f-1172",
                "entity-ner": "money",
                "entity-specificity": "UNK",
                "entity-text": "100,000 U.S. dollars"
            },
            {
                "reo": "reo::Donor",
                "ere": "giver",
                "entity": "ent-270",
                "entity-ner": "ORG",
                "entity-specificity": "specificIndividual",
                "entity-text": "the Chinese government"
            },
            {
                "reo": "reo::place",
                "ere": "place",
                "entity": "ent-30",
                "entity-ner": "LOC",
                "entity-specificity": "specificIndeterminate",
                "entity-text": "central Philippine regions ravaged by typhoon Haiyan, or locally known as Yolanda"
            }
        ]
    },
    {
        "event": {
            "reo": "reo::Give",
            "ere": "transfermoney",
            "lemma": "donation",
            "propbank": "donate.01",
            "mentionid": "em-1185",
            "modality": "actual",
            "framenet": "fn::Giving"
        },
        "arguments": [
            {
                "reo": "reo::CostOrCotheme",
                "ere": "money",
                "entity": "f-1202",
                "entity-ner": "money",
                "entity-specificity": "UNK",
                "entity-text": "100,000 U.S. dollars"
            },
            {
                "reo": "reo::Donor",
                "ere": "giver",
                "entity": "ent-285",
                "entity-ner": "ORG",
                "entity-specificity": "specificIndividual",
                "entity-text": "Chinese Red Cross Society"
            },
            {
                "reo": "reo::place",
                "ere": "place",
                "entity": "ent-30",
                "entity-ner": "LOC",
                "entity-specificity": "specificIndeterminate",
                "entity-text": "central Philippine regions ravaged by typhoon Haiyan, or locally known as Yolanda"
            }
        ]
    },
    {
        "event": {
            "reo": "reo::Accompanied_directed_caused_change_location",
            "ere": "transportartifact",
            "lemma": "delivered",
            "propbank": "delivered.XX",
            "mentionid": "em-1215",
            "modality": "actual",
            "framenet": "fn::Bringing"
        },
        "arguments": [
            {
                "reo": "reo::AccompaniedTheme",
                "ere": "artifact",
                "entity": "f-1232",
                "entity-ner": "commodity",
                "entity-specificity": "UNK",
                "entity-text": "The 73 million Pesos (1.67 million U.S. dollars) worth of relief goods"
            },
            {
                "reo": "reo::Destination",
                "ere": "destination",
                "entity": "ent-39",
                "entity-ner": "GPE",
                "entity-specificity": "specificIndividual",
                "entity-text": "Philippine"
            },
            {
                "reo": "reo::time",
                "ere": "time",
                "entity": "f-1247",
                "entity-ner": "time",
                "entity-specificity": "UNK",
                "entity-text": "Nov. 19"
            }
        ]
    },
    {
        "event": {
            "reo": "reo::Accompanied_directed_caused_change_location",
            "ere": "transportartifact",
            "lemma": "arrived",
            "propbank": "arrived.XX",
            "mentionid": "em-1252",
            "modality": "actual",
            "framenet": "fn::Bringing"
        },
        "arguments": [
            {
                "reo": "reo::AccompaniedTheme",
                "ere": "artifact",
                "entity": "f-1269",
                "entity-ner": "commodity",
                "entity-specificity": "UNK",
                "entity-text": "a cargo of 37.8 million pesos worth of supplies"
            },
            {
                "reo": "reo::Destination",
                "ere": "destination",
                "entity": "ent-330",
                "entity-ner": "GPE",
                "entity-specificity": "specificIndividual",
                "entity-text": "Cebu"
            },
            {
                "reo": "reo::time",
                "ere": "time",
                "entity": "f-1284",
                "entity-ner": "time",
                "entity-specificity": "UNK",
                "entity-text": "Nov. 21"
            }
        ]
    },
    {
        "event": {
            "reo": "reo::Steal",
            "ere": "transfermoney",
            "lemma": "dispatched",
            "propbank": "dispatched.XX",
            "mentionid": "em-1289",
            "modality": "actual",
            "framenet": "fn::Theft"
        },
        "arguments": [
            {
                "reo": "reo::Victim",
                "ere": "giver",
                "entity": "ent-8",
                "entity-ner": "GPE",
                "entity-specificity": "specificIndividual",
                "entity-text": "China"
            }
        ]
    },
    {
        "event": {
            "reo": "reo::Steal",
            "ere": "transferownership",
            "lemma": "dispatched",
            "propbank": "dispatched.XX",
            "mentionid": "em-1319",
            "modality": "actual",
            "framenet": "fn::Theft"
        },
        "arguments": [
            {
                "reo": "reo::Victim",
                "ere": "giver",
                "entity": "ent-8",
                "entity-ner": "GPE",
                "entity-specificity": "specificIndividual",
                "entity-text": "China"
            },
            {
                "reo": "reo::Theme",
                "ere": "thing",
                "entity": "f-1344",
                "entity-ner": "commodity",
                "entity-specificity": "UNK",
                "entity-text": "materials"
            }
        ]
    },
    {
        "event": {
            "reo": "reo::Send",
            "ere": "transportperson",
            "lemma": "dispatched",
            "propbank": "dispatch.01",
            "mentionid": "em-1349",
            "modality": "actual",
            "framenet": "fn::Sending"
        },
        "arguments": [
            {
                "reo": "reo::Agent",
                "ere": "agent",
                "entity": "ent-8",
                "entity-ner": "GPE",
                "entity-specificity": "specificIndividual",
                "entity-text": "China"
            },
            {
                "reo": "reo::Theme",
                "ere": "person",
                "entity": "ent-345",
                "entity-ner": "PER",
                "entity-specificity": "specificGroup",
                "entity-text": "three medical teams, including the country's largest hospital ship Peace Ark"
            },
            {
                "reo": "reo::Recipient",
                "ere": "destination",
                "entity": "ent-360",
                "entity-ner": "LOC",
                "entity-specificity": "specificIndeterminate",
                "entity-text": "hardest-hit areas in Eastern Visayas including Tacloban city"
            }
        ]
    },
    {
        "event": {
            "reo": "reo::UNK",
            "ere": "transaction",
            "lemma": "assistance",
            "propbank": "UNK",
            "mentionid": "em-1423",
            "modality": "actual",
            "framenet": "UNK"
        },
        "arguments": [
            {
                "reo": "UNK",
                "ere": "ere::Giver",
                "entity": "ent-8",
                "entity-ner": "GPE",
                "entity-specificity": "specificIndividual",
                "entity-text": "China"
            },
            {
                "reo": "UNK",
                "ere": "ere::Recipient",
                "entity": "ent-39",
                "entity-ner": "GPE",
                "entity-specificity": "specificIndividual",
                "entity-text": "Philippines"
            }
        ]
    },
    {
        "event": {
            "reo": "reo::Give",
            "ere": "transaction",
            "lemma": "giving",
            "propbank": "give.01",
            "mentionid": "em-1529",
            "modality": "actual",
            "framenet": "fn::Giving"
        },
        "arguments": [
            {
                "reo": "reo::Donor",
                "ere": "recipient",
                "entity": "ent-153",
                "entity-ner": "ORG",
                "entity-specificity": "specificIndividual",
                "entity-text": "Philippine Red Cross"
            }
        ]
    },
    {
        "event": {
            "reo": "reo::Meet",
            "ere": "meet",
            "lemma": "received",
            "propbank": "received.XX",
            "mentionid": "em-1453",
            "modality": "actual",
            "framenet": "fn::Social_event"
        },
        "arguments": [
            {
                "reo": "reo::Meeting_Parties",
                "ere": "entity",
                "entity": "ent-402",
                "entity-ner": "PER",
                "entity-specificity": "specificGroup",
                "entity-text": "more than 3, 500 patients"
            }
        ]
    },
    {
        "event": {
            "reo": "reo::Lecture",
            "ere": "broadcast",
            "lemma": "said",
            "propbank": "said.XX",
            "mentionid": "em-1506",
            "modality": "actual",
            "framenet": "fn::Speak_on_topic"
        },
        "arguments": [
            {
                "reo": "reo::Audience",
                "ere": "audience",
                "entity": "ent-420",
                "entity-ner": "PER",
                "entity-specificity": "nonspecific",
                "entity-text": "the Chinese people"
            }
        ]
    },
    {
        "event": {
            "reo": "reo::Experience_Injury",
            "ere": "injure",
            "lemma": "injured",
            "propbank": "injure.01",
            "mentionid": "em-1631",
            "modality": "actual",
            "framenet": "fn::Experience_bodily_harm"
        },
        "arguments": [
            {
                "reo": "reo::Victim",
                "ere": "victim",
                "entity": "ent-627",
                "entity-ner": "PER",
                "entity-specificity": "specificGroup",
                "entity-text": "26,233 others"
            }
        ]
    },
    {
        "event": {
            "reo": "reo::Lecture",
            "ere": "broadcast",
            "lemma": "said",
            "propbank": "said.XX",
            "mentionid": "em-1559",
            "modality": "actual",
            "framenet": "fn::Speak_on_topic"
        },
        "arguments": [
            {
                "reo": "reo::Audience",
                "ere": "entity",
                "entity": "ent-546",
                "entity-ner": "PER",
                "entity-specificity": "specificIndividual",
                "entity-text": "Wang Yong"
            }
        ]
    },
    {
        "event": {
            "reo": "reo::Caused_leave-Remove",
            "ere": "transportperson",
            "lemma": "displaced",
            "propbank": "displaced.XX",
            "mentionid": "em-1652",
            "modality": "actual",
            "framenet": "fn::Removing"
        },
        "arguments": [
            {
                "reo": "reo::Agent",
                "ere": "agent",
                "entity": "ent-654",
                "entity-ner": "PER",
                "entity-specificity": "specificGroup",
                "entity-text": "4 million"
            }
        ]
    },
    {
        "event": {
            "reo": "reo::UNK",
            "ere": "meet",
            "lemma": "ceremony",
            "propbank": "UNK",
            "mentionid": "em-1738",
            "modality": "actual",
            "framenet": "UNK"
        },
        "arguments": [
            {
                "reo": "UNK",
                "ere": "ere::Place",
                "entity": "ent-174",
                "entity-ner": "FAC",
                "entity-specificity": "specificIndividual",
                "entity-text": "PRCS headquarters in Manila"
            },
            {
                "reo": "UNK",
                "ere": "ere::Entity",
                "entity": "ent-153",
                "entity-ner": "ORG",
                "entity-specificity": "specificIndividual",
                "entity-text": "Philippine Red Cross Society"
            }
        ]
    },
    {
        "event": {
            "reo": "reo::Get",
            "ere": "transferownership",
            "lemma": "delivered",
            "propbank": "delivered.XX",
            "mentionid": "em-1782",
            "modality": "actual",
            "framenet": "fn::Taking"
        },
        "arguments": [
            {
                "reo": "reo::Recipient",
                "ere": "recipient",
                "entity": "ent-39",
                "entity-ner": "GPE",
                "entity-specificity": "specificIndividual",
                "entity-text": "Philippine"
            },
            {
                "reo": "reo::time",
                "ere": "time",
                "entity": "f-1807",
                "entity-ner": "time",
                "entity-specificity": "UNK",
                "entity-text": "Nov. 19"
            },
            {
                "reo": "reo::Theme",
                "ere": "thing",
                "entity": "f-1814",
                "entity-ner": "commodity",
                "entity-specificity": "UNK",
                "entity-text": "The 73 million Pesos (1.67 million U.S. dollars) worth of relief goods"
            }
        ]
    },
    {
        "event": {
            "reo": "reo::Give",
            "ere": "transferownership",
            "lemma": "arrived",
            "propbank": "arrived.XX",
            "mentionid": "em-1819",
            "modality": "actual",
            "framenet": "fn::Giving"
        },
        "arguments": [
            {
                "reo": "reo::place",
                "ere": "place",
                "entity": "ent-330",
                "entity-ner": "GPE",
                "entity-specificity": "specificIndividual",
                "entity-text": "Cebu"
            },
            {
                "reo": "reo::time",
                "ere": "time",
                "entity": "f-1844",
                "entity-ner": "time",
                "entity-specificity": "UNK",
                "entity-text": "Nov. 21"
            },
            {
                "reo": "reo::Theme",
                "ere": "thing",
                "entity": "f-1851",
                "entity-ner": "commodity",
                "entity-specificity": "UNK",
                "entity-text": "a cargo of 37.8 million pesos worth of supplies"
            }
        ]
    },
    {
        "event": {
            "reo": "reo::Accompanied_directed_caused_change_location",
            "ere": "transportartifact",
            "lemma": "dispatched",
            "propbank": "dispatched.XX",
            "mentionid": "em-1856",
            "modality": "actual",
            "framenet": "fn::Bringing"
        },
        "arguments": [
            {
                "reo": "reo::Mover",
                "ere": "agent",
                "entity": "ent-8",
                "entity-ner": "GPE",
                "entity-specificity": "specificIndividual",
                "entity-text": "China"
            },
            {
                "reo": "reo::AccompaniedTheme",
                "ere": "artifact",
                "entity": "f-1881",
                "entity-ner": "commodity",
                "entity-specificity": "UNK",
                "entity-text": "materials"
            }
        ]
    }
]