[
    {
        "event": {
            "reo": "reo::Arrest",
            "ere": "arrestjail",
            "lemma": "prison",
            "propbank": "prison.XX",
            "mentionid": "em-568eb23c_60_464",
            "modality": "actual",
            "framenet": "fn::Arrest"
        },
        "arguments": [
            {
                "reo": "reo::Suspect",
                "ere": "person",
                "entity": "ent-m.0f1lfn",
                "entity-ner": "PER",
                "entity-specificity": "specific",
                "entity-text": "Oscar Pistorius"
            },
            {
                "reo": "reo::place",
                "ere": "place",
                "entity": "ent-568eb23c_60_189",
                "entity-ner": "FAC",
                "entity-specificity": "specific",
                "entity-text": "prison"
            }
        ]
    },
    {
        "event": {
            "reo": "reo::Arrest",
            "ere": "arrestjail",
            "lemma": "prison",
            "propbank": "prison.XX",
            "mentionid": "em-568eb23c_60_492",
            "modality": "generic",
            "framenet": "fn::Arrest"
        },
        "arguments": [
            {
                "reo": "reo::Suspect",
                "ere": "person",
                "entity": "ent-568eb23c_60_213",
                "entity-ner": "PER",
                "entity-specificity": "nonspecific",
                "entity-text": "their"
            },
            {
                "reo": "reo::place",
                "ere": "place",
                "entity": "ent-568eb23c_60_252",
                "entity-ner": "FAC",
                "entity-specificity": "nonspecific",
                "entity-text": "prison"
            }
        ]
    },
    {
        "event": {
            "reo": "reo::UNK",
            "ere": "correspondence",
            "lemma": "speak",
            "propbank": "UNK",
            "mentionid": "em-568eb23c_60_545",
            "modality": "actual",
            "framenet": "UNK"
        },
        "arguments": [
            {
                "reo": "UNK",
                "ere": "ere::Entity",
                "entity": "ent-568eb23c_60_216",
                "entity-ner": "PER",
                "entity-specificity": "nonspecific",
                "entity-text": "we"
            }
        ]
    },
    {
        "event": {
            "reo": "reo::Arrest",
            "ere": "arrestjail",
            "lemma": "prison",
            "propbank": "prison.XX",
            "mentionid": "em-568eb23c_60_566",
            "modality": "generic",
            "framenet": "fn::Arrest"
        },
        "arguments": [
            {
                "reo": "reo::Suspect",
                "ere": "person",
                "entity": "ent-568eb23c_60_372",
                "entity-ner": "PER",
                "entity-specificity": "nonspecific",
                "entity-text": "nobody that is in prison"
            },
            {
                "reo": "reo::place",
                "ere": "place",
                "entity": "ent-568eb23c_60_252",
                "entity-ner": "FAC",
                "entity-specificity": "nonspecific",
                "entity-text": "prison"
            }
        ]
    },
    {
        "event": {
            "reo": "reo::Get",
            "ere": "transferownership",
            "lemma": "gets",
            "propbank": "get.01",
            "mentionid": "em-568eb23c_60_626",
            "modality": "other",
            "framenet": "fn::Getting"
        },
        "arguments": [
            {
                "reo": "reo::Recipient",
                "ere": "recipient",
                "entity": "ent-m.0f1lfn",
                "entity-ner": "PER",
                "entity-specificity": "specific",
                "entity-text": "he"
            },
            {
                "reo": "reo::Theme",
                "ere": "thing",
                "entity": "f-568eb23c_60_651",
                "entity-ner": "commodity",
                "entity-specificity": "UNK",
                "entity-text": "a multi million firepool"
            }
        ]
    },
    {
        "event": {
            "reo": "reo::UNK",
            "ere": "transportperson",
            "lemma": "drive",
            "propbank": "UNK",
            "mentionid": "em-568eb23c_60_656",
            "modality": "other",
            "framenet": "UNK"
        },
        "arguments": [
            {
                "reo": "UNK",
                "ere": "ere::Agent",
                "entity": "ent-m.0f1lfn",
                "entity-ner": "PER",
                "entity-specificity": "specific",
                "entity-text": "his"
            },
            {
                "reo": "UNK",
                "ere": "ere::Instrument",
                "entity": "f-568eb23c_60_681",
                "entity-ner": "vehicle",
                "entity-specificity": "UNK",
                "entity-text": "his mclaren"
            }
        ]
    }
]